AUTHORS
CHANGELOG
INSTALL
LICENSE
MANIFEST.in
README.rst
VERSION
setup.cfg
setup.py
djangoplicity_python_xmp_toolkit.egg-info/PKG-INFO
djangoplicity_python_xmp_toolkit.egg-info/SOURCES.txt
djangoplicity_python_xmp_toolkit.egg-info/dependency_links.txt
djangoplicity_python_xmp_toolkit.egg-info/top_level.txt
docs/html/.buildinfo
docs/html/appendix.html
docs/html/developers.html
docs/html/genindex.html
docs/html/index.html
docs/html/installation.html
docs/html/introduction.html
docs/html/objects.inv
docs/html/reference.html
docs/html/search.html
docs/html/searchindex.js
docs/html/using.html
docs/html/_sources/appendix.txt
docs/html/_sources/developers.txt
docs/html/_sources/index.txt
docs/html/_sources/installation.txt
docs/html/_sources/introduction.txt
docs/html/_sources/reference.txt
docs/html/_sources/using.txt
docs/html/_static/basic.css
docs/html/_static/default.css
docs/html/_static/doctools.js
docs/html/_static/file.png
docs/html/_static/jquery.js
docs/html/_static/minus.png
docs/html/_static/plus.png
docs/html/_static/pygments.css
docs/html/_static/searchtools.js
docs/html/_static/sidebar.js
docs/html/_static/underscore.js
libxmp/__init__.py
libxmp/consts.py
libxmp/core.py
libxmp/exceptions.py
libxmp/files.py
libxmp/types.py
libxmp/utils.py
test/samples.py
test/test_all.py
test/test_core.py
test/test_core_unit.py
test/test_files.py
test/xmpcoverage.py
test/fixtures/BlueSquare450.tif
test/fixtures/BlueSquare450.xmp
test/fixtures/empty.txt
test/samples/BlueSquare.ai
test/samples/BlueSquare.avi
test/samples/BlueSquare.eps
test/samples/BlueSquare.gif
test/samples/BlueSquare.indd
test/samples/BlueSquare.jpg
test/samples/BlueSquare.mov
test/samples/BlueSquare.mp3
test/samples/BlueSquare.pdf
test/samples/BlueSquare.png
test/samples/BlueSquare.psd
test/samples/BlueSquare.tif
test/samples/BlueSquare.wav
test/samples/BlueSquare.xmp
test/samples/sig05-002a.tif
test/samples/sig05-002a.xmp
test/samples/sig05-003a.xmp