Metadata-Version: 2.1
Name: djangoplicity-python-xmp-toolkit
Version: 1.0.2
Summary: Python XMP Toolkit for working with metadata.
Home-page: https://github.com/djangoplicity/djangoplicity-python-xmp-toolkit
Download-URL: https://github.com/djangoplicity/djangoplicity-python-xmp-toolkit/archive/refs/tags/1.0.2.tar.gz
Author: Lars Holm Nielsen, Federico Caboni & Amit Kapadia
Author-email: lnielsen@eso.org,federico.caboni@me.com,akapad@gmail.com
License: New BSD License
License-File: LICENSE
License-File: AUTHORS
